<?xml version="1.0" encoding="UTF-8"?>
<manifest>

  <!-- General repos -->
  <remove-project name="platform/build" />
  <remove-project name="platform/build/soong" />
  <remove-project name="platform/bionic" />
  <remove-project name="platform/external/selinux" />
  <remove-project name="platform/external/tinycompress" />
  <remove-project name="platform/frameworks/av" />
  <remove-project name="platform/frameworks/base" />
  <remove-project name="platform/frameworks/native" />
  <remove-project name="platform/hardware/libhardware" />
  <remove-project name="platform/hardware/libhardware_legacy" />
  <remove-project name="platform/hardware/qcom/bt" />
  <remove-project name="platform/hardware/qcom/wlan" />
  <remove-project name="platform/hardware/ril" />
  <remove-project name="platform/packages/providers/MediaProvider" />
  <remove-project name="platform/packages/services/Telephony" />
  <remove-project name="platform/system/bt" />
  <remove-project name="platform/system/core" />
  <remove-project name="platform/system/sepolicy" />
  <remove-project name="platform/system/vold" />
     
  <remove-project name="platform/packages/apps/Launcher2" />
  <remove-project name="platform/bootable/recovery" />
  <remove-project name="platform/packages/apps/DeskClock" />
  <remove-project name="platform/packages/apps/Messaging" />
  
  <!-- Track Our AOSP repos -->
  <include name="Ours.xml" />

</manifest>
